MANIFEST.in
README.rst
requirements.txt
setup.py
botsock/__init__.py
botsock/client.py
botsock/exceptions.py
botsock/server.py
botsock/settings.py
botsock/utils.py
botsock.egg-info/PKG-INFO
botsock.egg-info/SOURCES.txt
botsock.egg-info/dependency_links.txt
botsock.egg-info/requires.txt
botsock.egg-info/top_level.txt