Metadata-Version: 1.0
Name: botsock
Version: 0.0.4
Summary: secure socket server for bot communication
Home-page: https://github.com/ostrbor/botsock
Author: Boris Ostretsov
Author-email: ostrbor@gmail.com
License: MIT
Keywords: bot botnet socket server
Platform: UNKNOWN
